README.md
setup.py
netbox_plugin_reloader/__init__.py
netbox_plugin_reloader/version.py
netbox_plugin_reloader.egg-info/PKG-INFO
netbox_plugin_reloader.egg-info/SOURCES.txt
netbox_plugin_reloader.egg-info/dependency_links.txt
netbox_plugin_reloader.egg-info/not-zip-safe
netbox_plugin_reloader.egg-info/top_level.txt