Metadata-Version: 2.4
Name: netbox-plugin-reloader
Version: 4.5.0.1
Summary: Dynamically reload NetBox plugins without server restart
Home-page: https://github.com/Kani999/netbox-plugin-reloader
Author: Jan Krupa
License: Apache 2
Keywords: netbox,netbox-plugin
Classifier: Intended Audience :: Developers
Classifier: Framework :: Django
Classifier: Framework :: Django :: 5.1
Classifier: License :: OSI Approved :: Apache Software License
Classifier: Programming Language :: Python :: 3
Classifier: Programming Language :: Python :: 3.12
Classifier: Programming Language :: Python :: 3.13
Classifier: Operating System :: OS Independent
Requires-Python: >=3.12
Dynamic: author
Dynamic: classifier
Dynamic: description
Dynamic: description-content-type
Dynamic: home-page
Dynamic: keywords
Dynamic: license
Dynamic: requires-python
Dynamic: summary
